AudioPlaza/__init__.py
AudioPlaza/downsample.py
AudioPlaza/duration.py
AudioPlaza/googledrive.py
AudioPlaza/trim1.py
AudioPlaza/trim2.py
AudioPlaza-0.1.2.dist-info/METADATA
AudioPlaza-0.1.2.dist-info/WHEEL
AudioPlaza-0.1.2.dist-info/top_level.txt
AudioPlaza-0.1.2.dist-info/RECORD
