Metadata-Version: 2.1
Name: AudioPlaza
Version: 0.1.2
Summary: AudioPlaza: RAONDATA speech team's Audio Preprocessing written by python
Home-page: https://github.com/raondata/AudioPlaza
Author: RAONDATA speech team
Author-email: kojunseo@raondata.ai
License: Raondata Private
Classifier: Programming Language :: Python :: 3
Classifier: License :: OSI Approved :: MIT License
Classifier: Operating System :: OS Independent
Requires-Python: >=3.6
Requires-Dist: torchaudio
Requires-Dist: soundfile
Requires-Dist: plotly
Requires-Dist: tqdm
Requires-Dist: numpy
